kannon/__init__.py
kannon/kube_util.py
kannon/master.py
kannon/task.py
kannon-0.1.4.dist-info/LICENSE
kannon-0.1.4.dist-info/METADATA
kannon-0.1.4.dist-info/WHEEL
kannon-0.1.4.dist-info/RECORD
